odoo10_addon_l10n_it_account_stamp_sale-10.0.1.0.1-py2.7-nspkg.pth
odoo/addons/l10n_it_account_stamp_sale/README.rst
odoo/addons/l10n_it_account_stamp_sale/__init__.py
odoo/addons/l10n_it_account_stamp_sale/__manifest__.py
odoo/addons/l10n_it_account_stamp_sale/i18n/l10n_it_account_stamp_sale.pot
odoo/addons/l10n_it_account_stamp_sale/models/__init__.py
odoo/addons/l10n_it_account_stamp_sale/models/sale_order.py
odoo/addons/l10n_it_account_stamp_sale/readme/CONTRIBUTORS.rst
odoo/addons/l10n_it_account_stamp_sale/readme/DESCRIPTION.rst
odoo/addons/l10n_it_account_stamp_sale/static/description/icon.png
odoo/addons/l10n_it_account_stamp_sale/static/description/index.html
odoo10_addon_l10n_it_account_stamp_sale-10.0.1.0.1.dist-info/METADATA
odoo10_addon_l10n_it_account_stamp_sale-10.0.1.0.1.dist-info/RECORD
odoo10_addon_l10n_it_account_stamp_sale-10.0.1.0.1.dist-info/WHEEL
odoo10_addon_l10n_it_account_stamp_sale-10.0.1.0.1.dist-info/namespace_packages.txt
odoo10_addon_l10n_it_account_stamp_sale-10.0.1.0.1.dist-info/top_level.txt
