Metadata-Version: 2.1
Name: odoo10-addon-l10n-it-account-stamp-sale
Version: 10.0.1.0.1
Summary: Modulo ponte tra imposta di bollo e vendite
Home-page: https://github.com/OCA/l10n-italy/tree/10.0/l10n_it_account_stamp_sale
Author: Agile Business Group, Odoo Community Association (OCA)
Author-email: support@odoo-community.org
License: AGPL-3
Platform: UNKNOWN
Classifier: Programming Language :: Python
Classifier: Framework :: Odoo
Classifier: License :: OSI Approved :: GNU Affero General Public License v3
Requires-Python: ~=2.7
Requires-Dist: odoo10-addon-l10n-it-account-stamp
Requires-Dist: odoo (<10.1dev,>=10.0)
